postnlecommerce/__init__.py
postnlecommerce/api_helper.py
postnlecommerce/configuration.py
postnlecommerce/postnlecommerce_client.py
postnlecommerce/controllers/__init__.py
postnlecommerce/controllers/barcode_controller.py
postnlecommerce/controllers/base_controller.py
postnlecommerce/controllers/checkout_controller.py
postnlecommerce/controllers/confirming_controller.py
postnlecommerce/controllers/deliverydate_controller.py
postnlecommerce/controllers/labelling_controller.py
postnlecommerce/controllers/locations_controller.py
postnlecommerce/controllers/postalcode_check_controller.py
postnlecommerce/controllers/shipment_controller.py
postnlecommerce/controllers/shipping_status_controller.py
postnlecommerce/controllers/timeframes_controller.py
postnlecommerce/exceptions/__init__.py
postnlecommerce/exceptions/api_exception.py
postnlecommerce/exceptions/barcode_response_invalid_exception.py
postnlecommerce/exceptions/confirming_response_error_exception.py
postnlecommerce/exceptions/internal_server_error_exception.py
postnlecommerce/exceptions/invalid_request_exception.py
postnlecommerce/exceptions/labelling_response_invalid_exception.py
postnlecommerce/exceptions/method_not_allowed_only_get_exception.py
postnlecommerce/exceptions/method_not_allowed_only_get_post_exception.py
postnlecommerce/exceptions/method_not_allowed_only_post_exception.py
postnlecommerce/exceptions/postalcode_check_response_invalid_exception.py
postnlecommerce/exceptions/too_many_requests_exception.py
postnlecommerce/exceptions/unauthorized_exception.py
postnlecommerce/http/__init__.py
postnlecommerce/http/api_response.py
postnlecommerce/http/http_call_back.py
postnlecommerce/http/http_method_enum.py
postnlecommerce/http/http_request.py
postnlecommerce/http/http_response.py
postnlecommerce/http/auth/__init__.py
postnlecommerce/http/auth/custom_header_authentication.py
postnlecommerce/models/__init__.py
postnlecommerce/models/address.py
postnlecommerce/models/address_type_enum.py
postnl_ecommerce_sdk-1.0.5.dist-info/LICENSE
postnl_ecommerce_sdk-1.0.5.dist-info/METADATA
postnl_ecommerce_sdk-1.0.5.dist-info/WHEEL
postnl_ecommerce_sdk-1.0.5.dist-info/top_level.txt
postnl_ecommerce_sdk-1.0.5.dist-info/RECORD
